awsenviron.py
awsenviron-0.0.7.dist-info/DESCRIPTION.rst
awsenviron-0.0.7.dist-info/METADATA
awsenviron-0.0.7.dist-info/RECORD
awsenviron-0.0.7.dist-info/WHEEL
awsenviron-0.0.7.dist-info/metadata.json
awsenviron-0.0.7.dist-info/top_level.txt
