Metadata-Version: 2.0
Name: awsenviron
Version: 0.0.7
Summary: Load environ vars from AWS Parameter Store
Home-page: https://github.com/douglasfarinelli/python-awsenviron
Author: Douglas Farinelli
Author-email: douglas.farinelli@gmail.com
License: MIT
Keywords: env python aws parameter-store
Platform: any
Classifier: Intended Audience :: Developers
Classifier: License :: OSI Approved :: MIT License
Classifier: Operating System :: OS Independent
Classifier: Programming Language :: Python :: 2.7
Classifier: Programming Language :: Python :: 3
Classifier: Programming Language :: Python :: 3.6
Requires-Python: >=2.7
Requires-Dist: boto3
